fcust/__init__.py
fcust/cli.py
fcust/fcust.py
fcust/service.py
usr/share/man/man1/fcust.1
fcust-1.0.0.dist-info/AUTHORS.rst
fcust-1.0.0.dist-info/LICENSE
fcust-1.0.0.dist-info/METADATA
fcust-1.0.0.dist-info/WHEEL
fcust-1.0.0.dist-info/entry_points.txt
fcust-1.0.0.dist-info/top_level.txt
fcust-1.0.0.dist-info/RECORD
