Metadata-Version: 2.1
Name: fcust
Version: 1.0.0
Summary: Linux Common Folder Custodian
Home-page: https://github.com/Iolaum/fcust
Author: Nikolaos Perrakis
Author-email: nikperrakis@gmail.com
License: GNU General Public License v3
Keywords: fcust
Platform: UNKNOWN
Classifier: Development Status :: 5 - Production/Stable
Classifier: Intended Audience :: End Users/Desktop
Classifier: License :: OSI Approved :: GNU General Public License v3 (GPLv3)
Classifier: Natural Language :: English
Classifier: Programming Language :: Python :: 3
Classifier: Programming Language :: Python :: 3.9
Classifier: Programming Language :: Python :: 3.10
Requires-Python: >=3.8
License-File: LICENSE
License-File: AUTHORS.rst
Requires-Dist: Click (>=7.1)
Provides-Extra: dev
Requires-Dist: pip ; extra == 'dev'
Requires-Dist: bump2version (>=1.0) ; extra == 'dev'
Requires-Dist: wheel ; extra == 'dev'
Requires-Dist: Sphinx ; extra == 'dev'
Requires-Dist: twine ; extra == 'dev'
Requires-Dist: check-manifest ; extra == 'dev'
Requires-Dist: pytest ; extra == 'dev'
Requires-Dist: pytest-runner ; extra == 'dev'
Requires-Dist: mock ; extra == 'dev'
Requires-Dist: flake8 ; extra == 'dev'
Requires-Dist: black ; extra == 'dev'
Requires-Dist: mypy ; extra == 'dev'
Requires-Dist: coverage ; extra == 'dev'
Requires-Dist: yamllint ; extra == 'dev'
Requires-Dist: doc8 ; extra == 'dev'
Requires-Dist: pluggy ; extra == 'dev'
Requires-Dist: docutils (==0.17) ; extra == 'dev'
